README
setup.py
src/SpiffWarehouse/DB.py
src/SpiffWarehouse/Item.py
src/SpiffWarehouse/__init__.py
src/SpiffWarehouse/functions.py
src/SpiffWarehouse.egg-info/PKG-INFO
src/SpiffWarehouse.egg-info/SOURCES.txt
src/SpiffWarehouse.egg-info/dependency_links.txt
src/SpiffWarehouse.egg-info/top_level.txt