Metadata-Version: 1.0
Name: SpiffWarehouse
Version: 0.2.0
Summary: A library for storing revisioned files
Home-page: http://code.google.com/p/spiff-warehouse/
Author: Samuel Abels
Author-email: cheeseshop.python.org@debain.org
License: GPLv2
Keywords: spiff warehouse object storage revisioning
Platform: UNKNOWN
Classifier: Development Status :: 5 - Production/Stable
Classifier: Intended Audience :: Developers
Classifier: License :: OSI Approved :: GNU General Public License (GPL)
Classifier: Programming Language :: Python
Classifier: Topic :: Software Development :: Libraries
Classifier: Topic :: Software Development :: Libraries :: Python Modules
